sumojfrogxray/__init__.py
sumojfrogxray/api.py
sumojfrogxray/jfrogxraycollector.yaml
sumojfrogxray/main.py
sumologic_jfrog_xray-1.0.3.dist-info/LICENSE
sumologic_jfrog_xray-1.0.3.dist-info/METADATA
sumologic_jfrog_xray-1.0.3.dist-info/WHEEL
sumologic_jfrog_xray-1.0.3.dist-info/entry_points.txt
sumologic_jfrog_xray-1.0.3.dist-info/top_level.txt
sumologic_jfrog_xray-1.0.3.dist-info/zip-safe
sumologic_jfrog_xray-1.0.3.dist-info/RECORD
