Metadata-Version: 2.1
Name: sumologic-jfrog-xray
Version: 1.0.3
Summary: Sumo Logic collection solution for JFrog Xray.
Home-page: https://github.com/SumoLogic/sumologic-jfrog-xray
Author: SumoLogic
Author-email: it@sumologic.com, apps-team@sumologic.com
License: PSF
Keywords: sumologic python rest api log management analytics logreduce Jfrog Xray agent security siem collector forwarder
Platform: UNKNOWN
Classifier: Development Status :: 4 - Beta
Classifier: Intended Audience :: Developers
Classifier: Programming Language :: Python :: 2.7
Classifier: Programming Language :: Python :: 3.7
Classifier: Operating System :: OS Independent
Requires-Dist: sumologic-appclient-sdk (==1.0.17)
